LICENSE
MANIFEST.in
README.md
pyproject.toml
setup.py
fast_minh/CMakeLists.txt
fast_minh/MurmurHash3.cpp
fast_minh/MurmurHash3.h
fast_minh/__init__.py
fast_minh/fast_minh.cpp
fast_minh/fast_minh.h
fast_minh.egg-info/PKG-INFO
fast_minh.egg-info/SOURCES.txt
fast_minh.egg-info/dependency_links.txt
fast_minh.egg-info/requires.txt
fast_minh.egg-info/top_level.txt
fast_minh/utils/__init__.py
fast_minh/utils/estimate.py